{  
    "hitbox": "player",
    "resourceIdentifier": "cobblemon:gentleman",
    "presets": ["cobblemon:trainer_basics"],
    "interaction": {
        "type": "dialogue",
        "dialogue": "cobblemon:gentlemangregory_interaction"
    },
        "name": "Gregory",
        "party": {
        "type": "simple",
        "pokemon": [
            "Pikachu level=46",
            "Flaaffy level=43",
            "Electrike level=42"
        ]
    },
    "config": [
        {
            "variableName": "can_rechallenge",
            "displayName": "Rechallenging",
            "description": "This NPC can be battled multiple times.",
            "type": "BOOLEAN",
            "defaultValue": true
        },
        {
            "variableName": "on_player_wins",
            "displayName": "npc.variable.on_player_wins.name",
            "description": "npc.variable.on_player_wins.desc",
            "type": "TEXT",
            "defaultValue": "q.run_command('execute as ' + q.player.username + ' run opendialogue gentlemangregory_end @s');"
          }
    ]
}
